auto_teacher_process/README.md
auto_teacher_process/__init__.py
auto_teacher_process/config.py
auto_teacher_process/consts.py
auto_teacher_process/logger.py
auto_teacher_process/main.py
auto_teacher_process/db/README.md
auto_teacher_process/db/__init__.py
auto_teacher_process/db/db_base.py
auto_teacher_process/db/services/db_add_new_paper.py
auto_teacher_process/db/services/db_associated_teacher_leader.py
auto_teacher_process/db/services/db_google_match.py
auto_teacher_process/db/services/db_insert_cn_paper_match.py
auto_teacher_process/db/services/db_insert_dedup.py
auto_teacher_process/db/services/db_insert_des_paper.py
auto_teacher_process/db/services/db_insert_experience.py
auto_teacher_process/db/services/db_insert_famous_projects.py
auto_teacher_process/db/services/db_insert_host_project.py
auto_teacher_process/db/services/db_insert_html.py
auto_teacher_process/db/services/db_insert_infos.py
auto_teacher_process/db/services/db_insert_name.py
auto_teacher_process/db/services/db_insert_paper_match.py
auto_teacher_process/db/services/db_insert_patent_match.py
auto_teacher_process/db/services/db_insert_project_match.py
auto_teacher_process/db/services/db_insert_relation.py
auto_teacher_process/db/services/db_insert_teacher_level.py
auto_teacher_process/db/services/db_teacher_disappear.py
auto_teacher_process/db/services/db_update_infos.py
auto_teacher_process/db/services/es_operator.py
auto_teacher_process/db/test/old_famous_titles_test_data.csv
auto_teacher_process/db/test/project_level_test_data.csv
auto_teacher_process/db/test/teacher_level_test_data.csv
auto_teacher_process/db/test/test_async_db_execute_query.py
auto_teacher_process/db/test/test_db_associated_teacher_leader.py
auto_teacher_process/db/test/test_db_insert_dedup.py
auto_teacher_process/db/test/test_db_insert_des_paper.py
auto_teacher_process/db/test/test_db_insert_famous_projects.py
auto_teacher_process/db/test/test_db_insert_host_project.py
auto_teacher_process/db/test/test_db_insert_html.py
personnel_matching_data_process_algo_v2-0.0.1b8.dist-info/METADATA
personnel_matching_data_process_algo_v2-0.0.1b8.dist-info/WHEEL
personnel_matching_data_process_algo_v2-0.0.1b8.dist-info/entry_points.txt
personnel_matching_data_process_algo_v2-0.0.1b8.dist-info/licenses/LICENSE
personnel_matching_data_process_algo_v2-0.0.1b8.dist-info/RECORD
