Metadata-Version: 2.4
Name: personnel_matching_data_process_algo_v2
Version: 0.0.1b8
Summary: Behold My Awesome Project!
Author-email: GZHU <gzhu@example.com>
License-File: LICENSE
Requires-Python: >=3.11
Requires-Dist: aio-pika>=9.5.5
Requires-Dist: aiohttp==3.11.10
Requires-Dist: aiomysql==0.2.0
Requires-Dist: cryptography==44.0.1
Requires-Dist: dotenv>=0.9.9
Requires-Dist: elasticsearch==8.18.1
Requires-Dist: html2text==2025.4.15
Requires-Dist: langdetect==1.0.9
Requires-Dist: loguru>=0.7.3
Requires-Dist: openai==1.96.1
Requires-Dist: pandas==2.3.1
Requires-Dist: poethepoet>=0.36.0
Requires-Dist: pyarrow>=21.0.0
Requires-Dist: pydantic>=2.11.7
Requires-Dist: pymysql==1.1.1
Requires-Dist: pypinyin==0.54.0
Requires-Dist: pytest-asyncio==1.0.0
Requires-Dist: pytest-mock>=3.14.1
Requires-Dist: python-dotenv>=1.1.1
Requires-Dist: pyyaml==6.0.2
Requires-Dist: rapidfuzz>=3.13.0
Requires-Dist: redis>=6.2.0
Requires-Dist: sqlalchemy==2.0.39
Requires-Dist: tenacity==9.0.0
Requires-Dist: tqdm==4.67.1
Provides-Extra: release
Requires-Dist: poethepoet>=0.36.0; extra == 'release'
Requires-Dist: python-semantic-release>=10.2.0; extra == 'release'
